aiatools/__init__.py
aiatools/aia.py
aiatools/alexa-devices.json
aiatools/algebra.py
aiatools/attributes.py
aiatools/block_types.py
aiatools/common.py
aiatools/component_types.py
aiatools/selectors.py
aiatools/simple_components.json
aiatools-0.6.4.dist-info/licenses/COPYING
aiatools-0.6.4.dist-info/METADATA
aiatools-0.6.4.dist-info/WHEEL
aiatools-0.6.4.dist-info/top_level.txt
aiatools-0.6.4.dist-info/RECORD
