Metadata-Version: 2.4
Name: aiatools
Version: 0.6.4
Summary: Tools for extracting information from App Inventor AIA files
Author-email: "Evan W. Patton" <ewpatton@mit.edu>
Maintainer-email: "Evan W. Patton" <ewpatton@mit.edu>
License-Expression: GPL-3.0-or-later
Project-URL: Repository, https://github.com/mit-cml/aiatools
Keywords: App Inventor,AIA extraction,analysis,toolkit
Classifier: Development Status :: 3 - Alpha
Classifier: Environment :: Console
Classifier: Intended Audience :: Developers
Classifier: Intended Audience :: Education
Classifier: Intended Audience :: Science/Research
Classifier: Natural Language :: English
Classifier: Operating System :: OS Independent
Classifier: Programming Language :: Python
Classifier: Topic :: Education
Classifier: Topic :: Scientific/Engineering :: Information Analysis
Classifier: Topic :: Software Development
Classifier: Topic :: Utilities
Requires-Python: >=3.0
License-File: COPYING
Requires-Dist: jprops
Dynamic: license-file
